{"nodes": [{"id": "issuehunt_src_components_saved_statuscycler_tsx", "label": "StatusCycler.tsx", "file_type": "code", "source_file": "issuehunt\\src\\components\\saved\\StatusCycler.tsx", "source_location": "L1"}, {"id": "statuscycler_statuscycler", "label": "StatusCycler()", "file_type": "code", "source_file": "issuehunt\\src\\components\\saved\\StatusCycler.tsx", "source_location": "L32"}], "edges": [{"source": "issuehunt_src_components_saved_statuscycler_tsx", "target": "saved", "relation": "imports_from", "confidence": "EXTRACTED", "source_file": "issuehunt\\src\\components\\saved\\StatusCycler.tsx", "source_location": "L3", "weight": 1.0}, {"source": "issuehunt_src_components_saved_statuscycler_tsx", "target": "utils", "relation": "imports_from", "confidence": "EXTRACTED", "source_file": "issuehunt\\src\\components\\saved\\StatusCycler.tsx", "source_location": "L4", "weight": 1.0}, {"source": "issuehunt_src_components_saved_statuscycler_tsx", "target": "statuscycler_statuscycler", "relation": "contains", "confidence": "EXTRACTED", "source_file": "issuehunt\\src\\components\\saved\\StatusCycler.tsx", "source_location": "L32", "weight": 1.0}]}